flask_login_apple/__init__.py
flask_login_apple/auth.py
flask_login_apple-0.1.2.dist-info/METADATA
flask_login_apple-0.1.2.dist-info/WHEEL
flask_login_apple-0.1.2.dist-info/top_level.txt
flask_login_apple-0.1.2.dist-info/RECORD
